TerminalVideoPlayer/__init__.py
TerminalVideoPlayer/main.py
terminalvideoplayer-1.0.0.dist-info/METADATA
terminalvideoplayer-1.0.0.dist-info/WHEEL
terminalvideoplayer-1.0.0.dist-info/entry_points.txt
terminalvideoplayer-1.0.0.dist-info/licenses/LICENSE
terminalvideoplayer-1.0.0.dist-info/RECORD
