Metadata-Version: 2.4
Name: TerminalVideoPlayer
Version: 1.0.0
Summary: A TUI video player.
Project-URL: Homepage, https://github.com/Stu67nt/TerminalVideoPlayer
License-Expression: MIT
License-File: LICENSE
Classifier: Programming Language :: Python :: 3
Requires-Python: >=3.9
Requires-Dist: colorama
Requires-Dist: decord
Requires-Dist: fpstimer
Requires-Dist: numpy
Requires-Dist: playsound3
